sigmalint/__init__.py
sigmalint/schema/__init__.py
sigmalint/schema/schema.py
sigmalint/sigmalint.py
sigmalint-0.2.0.dist-info/entry_points.txt
sigmalint-0.2.0.dist-info/WHEEL
sigmalint-0.2.0.dist-info/METADATA
sigmalint-0.2.0.dist-info/RECORD
